rigl_torch/RigL.py
rigl_torch/__init__.py
rigl_torch/util.py
rigl_torch-0.5.2.dist-info/METADATA
rigl_torch-0.5.2.dist-info/WHEEL
rigl_torch-0.5.2.dist-info/top_level.txt
rigl_torch-0.5.2.dist-info/RECORD
