Metadata-Version: 2.1
Name: rigl-torch
Version: 0.5.2
Summary: Implementation of Google Research's "RigL" sparse model training method in PyTorch.
Home-page: https://github.com/McCrearyD/rigl-torch
Author: Dyllan McCreary
Author-email: mccreary@dyllan.ai
License: UNKNOWN
Platform: UNKNOWN
Classifier: Programming Language :: Python :: 3
Classifier: Operating System :: OS Independent
Requires-Python: >=3.6
